dj12/__init__.py
dj12/_bool.py
dj12/_email.py
dj12/config.py
dj12-0.3.0.dist-info/DESCRIPTION.rst
dj12-0.3.0.dist-info/METADATA
dj12-0.3.0.dist-info/RECORD
dj12-0.3.0.dist-info/WHEEL
dj12-0.3.0.dist-info/metadata.json
dj12-0.3.0.dist-info/top_level.txt
dj12-0.3.0.dist-info/zip-safe
