Metadata-Version: 2.0
Name: dj12
Version: 0.3.0
Summary: 12factor config support for Django
Home-page: https://gitlab.com/aiakos/dj12
Author: Aiakos Contributors
Author-email: aiakos@aiakosauth.com
License: MIT
Keywords: django 12factor configuration
Platform: UNKNOWN
Classifier: Development Status :: 4 - Beta
Classifier: Intended Audience :: Developers
Classifier: Intended Audience :: System Administrators
Classifier: License :: OSI Approved :: MIT License
Classifier: Programming Language :: Python
Classifier: Programming Language :: Python :: 2
Classifier: Programming Language :: Python :: 2.7
Classifier: Programming Language :: Python :: 3
Classifier: Programming Language :: Python :: 3.5
Classifier: Programming Language :: Python :: 3.6
Requires-Dist: dj-database-url
Requires-Dist: django
Requires-Dist: django-cache-url
Requires-Dist: six
